bepcar/fractions.py
bepcar/tools.py
bepcar-0.1.dist-info/METADATA
bepcar-0.1.dist-info/WHEEL
bepcar-0.1.dist-info/top_level.txt
bepcar-0.1.dist-info/RECORD
